{
  "Records": [
    {
      "EventSource": "aws:sns",
      "EventVersion": "1.0",
      "EventSubscriptionArn": "arn:{partition}:sns:EXAMPLE",
      "Sns": {
        "Type": "Notification",
        "MessageId": "95df01b4-ee98-5cb9-9903-4c221d41eb5e",
        "TopicArn": "arn:{partition}:sns:EXAMPLE",
        "Subject": "new",
        "Message": "{\"id\": \"a6k5A000000c0KAQAY\", \"title\": \"2-Pack: Studio Dry Infused Hair Turbans\", \"price_string\": \"$120\", \"deal_url\": \"https://meh.com/deals/2-pack-studio-dry-infused-hair-turbans/checkout\", \"image_url\": \"https://d2b8wt72ktn9a2.cloudfront.net/mediocre/image/upload/c_pad,f_auto,h_600,q_auto,w_600/acg06kfz2nduk8bxyr3q.gif\"}",
        "Timestamp": "2020-08-28T04:01:46.534Z",
        "Timestamp": "1970-01-01T00:00:00Z",
        "SignatureVersion": "1",
        "Signature": "EXAMPLE",
        "SigningCertUrl": "EXAMPLE",
        "UnsubscribeUrl": "EXAMPLE",
        "MessageAttributes": {
          "Test": {
            "Type": "String",
            "Value": "TestString"
          },
          "TestBinary": {
            "Type": "Binary",
            "Value": "TestBinary"
          }
        }
      }
    }
  ]
}
